gbnet/__init__.py
gbnet/base.py
gbnet/gblinear.py
gbnet/lgbmodule.py
gbnet/xgbmodule.py
gbnet/experimental/__init__.py
gbnet/experimental/catmodule.py
gbnet/models/__init__.py
gbnet/models/forecasting.py
gbnet/models/ordinal_regression.py
gbnet/models/survival/__init__.py
gbnet/models/survival/discrete_survival.py
gbnet/models/survival/hazard_integrator.py
gbnet/models/survival/hazard_survival.py
gbnet/models/survival/tests/__init__.py
gbnet/models/survival/tests/test_discrete_survival.py
gbnet/models/survival/tests/test_hazard_integrator.py
gbnet/models/survival/tests/test_hazard_survival.py
gbnet/models/tests/__init__.py
gbnet/models/tests/test_forecasting.py
gbnet/models/tests/test_ordinal_regression.py
gbnet/tests/__init__.py
gbnet/tests/test_base.py
gbnet/tests/test_gblinear.py
gbnet/tests/test_lgbmodule.py
gbnet/tests/test_readme_examples.py
gbnet/tests/test_xgbmodule.py
gbnet/tests/experimental/__init__.py
gbnet/tests/experimental/test_catmodule.py
gbnet-0.7.3.dist-info/licenses/LICENSE
gbnet-0.7.3.dist-info/METADATA
gbnet-0.7.3.dist-info/WHEEL
gbnet-0.7.3.dist-info/top_level.txt
gbnet-0.7.3.dist-info/RECORD
