Metadata-Version: 2.4
Name: gbnet
Version: 0.7.3
Summary: Gradient Boosting libraries integrated with PyTorch
Home-page: https://github.com/mthorrell/gbnet
Author: Michael Horrell
Author-email: mthorrell@github.com
License-File: LICENSE
Requires-Dist: numpy
Requires-Dist: torch
Dynamic: author
Dynamic: author-email
Dynamic: description
Dynamic: description-content-type
Dynamic: home-page
Dynamic: license-file
Dynamic: requires-dist
Dynamic: summary
